{"President":{"r_prec":3,"t_prec":1779,"candidates":[{"n":"Hillary Clinton","v":32686,"p":"D","d":"Democratic nominee","per":71.3},{"n":"Donald J. Trump","v":10786,"p":"R","d":"Republican nominee","per":23.5}]},"US Senator":{"r_prec":3,"t_prec":1779,"candidates":[{"n":"Patty Judge","v":28719,"p":"D","d":"Challenger - Democratic Party","per":64.0},{"n":"Charles E. Grassley","v":14732,"p":"R","d":"Incumbent - Republican Party","per":32.8}]},"US Rep. Dist. 1":{"r_prec":0,"t_prec":436,"candidates":[{"n":"Rod Blum","v":0,"p":"R","d":"Incumbent - Republican Party","per":0},{"n":"Monica Vernon","v":0,"p":"D","d":"Challenger - Democratic Party","per":0}]},"US Rep. Dist. 2":{"r_prec":2,"t_prec":424,"candidates":[{"n":"Dave Loebsack","v":31164,"p":"D","d":"Incumbent - Democratic Party","per":76.4},{"n":"Christopher Peters","v":9566,"p":"R","d":"Challenger - Republican Party","per":23.5}]},"US Rep. Dist. 3":{"r_prec":0,"t_prec":391,"candidates":[{"n":"David Young","v":0,"p":"R","d":"Incumbent - Republican Party","per":0},{"n":"Jim Mowrer","v":0,"p":"D","d":"Challenger - Democratic Party","per":0}]},"US Rep. Dist. 4":{"r_prec":1,"t_prec":528,"candidates":[{"n":"Steve King","v":2320,"p":"R","d":"Incumbent - Republican Party","per":61.0},{"n":"Kim Weaver","v":1483,"p":"D","d":"Challenger - Democratic Party","per":39.0}]}}